{
	"apps": [
		{"file":"com.zoodles.book.theemperorsnewclothes","title":"","type":"app","bounce":1,"scale":1},
		{"file":"com.zoodles.book.thethreelittlepigs","title":"","type":"app","bounce":1,"scale":1},
		{"file":"com.zoodles.book.thetortoiseandthehare","title":"","type":"app","bounce":1,"scale":1},
		{"file":"com.zoodles.book.thevelveteenrabbit","title":"","type":"app","bounce":1,"scale":1},
		{"file":"air.bftv.larryABCs","title":"","type":"app","bounce":1,"scale":1},
		{"file":"BMA_CO.Phonics_Lv1_Unit2","title":"","type":"app","bounce":1,"scale":1},
		{"file":"BMA_CO.Phonics_Lv1_Unit3","title":"","type":"app","bounce":1,"scale":1},
		{"file":"BMA_CO.Phonics_Lv1_Unit4","title":"","type":"app","bounce":1,"scale":1},
		{"file":"BMA_CO.Phonics_Lv1_Unit5","title":"","type":"app","bounce":1,"scale":1},
		{"file":"pl.ayground.littlepiano","title":"","type":"app","bounce":1,"scale":1},
		{"file":"russh.toddler.game","title":"","type":"app","bounce":1,"scale":1},
		{"file":"zok.android.shapes","title":"","type":"app","bounce":1,"scale":1},
		{"file":"BMA_CO.Phonics_Lv1_Unit6","title":"","type":"app","bounce":1,"scale":1},
		{"file":"edu.mit.media.prg.tinkerbook_unity","title":"","type":"app","bounce":1,"scale":1},
		{"file":"BMA_CO.Phonics_Lv1_Unit7","title":"","type":"app","bounce":1,"scale":1},
		{"file":"BMA_CO.Phonics_Lv1_Unit10","title":"","type":"app","bounce":1,"scale":1},
		{"file":"BMA_CO.Phonics_Lv1_Unit2","title":"","type":"app","bounce":1,"scale":1},
		{"file":"BMA_CO.Phonics_Lv1_Unit3","title":"","type":"app","bounce":1,"scale":1},
		{"file":"BMA_CO.Phonics_Lv1_Unit4","title":"","type":"app","bounce":1,"scale":1},
		{"file":"BMA_CO.Phonics_Lv1_Unit5","title":"","type":"app","bounce":1,"scale":1},
		{"file":"BMA_CO.Phonics_Lv1_Unit6","title":"","type":"app","bounce":1,"scale":1},
		{"file":"BMA_CO.Phonics_Lv1_Unit7","title":"","type":"app","bounce":1,"scale":1},
		{"file":"BMA_CO.Phonics_Lv1_Unit8","title":"","type":"app","bounce":1,"scale":1},
		{"file":"BMA_CO.Phonics_Lv1_Unit9","title":"","type":"app","bounce":1,"scale":1},
		{"file":"BMA_CO.Phonics_Lv2_Unit2","title":"","type":"app","bounce":1,"scale":1},
		{"file":"BMA_CO.Phonics_Lv2_Unit3","title":"","type":"app","bounce":1,"scale":1},
		{"file":"BMA_CO.Phonics_Lv2_Unit4","title":"","type":"app","bounce":1,"scale":1},
		{"file":"BMA_CO.Phonics_Lv2_Unit5","title":"","type":"app","bounce":1,"scale":1},
		{"file":"BMA_CO.Phonics_Lv2_Unit7","title":"","type":"app","bounce":1,"scale":1},
		{"file":"BMA_CO.Phonics_Lv2_Unit8","title":"","type":"app","bounce":1,"scale":1},
		{"file":"BMA_CO.Phonics_Lv2_Unit9","title":"","type":"app","bounce":1,"scale":1},
		{"file":"BMA_CO.Phonics_Lv2_Unit10","title":"","type":"app","bounce":1,"scale":1},
		{"file":"BMA_CO.Phonics_Lv3_Unit4","title":"","type":"app","bounce":1,"scale":1},
		{"file":"BMA_CO.Phonics_Lv3_Unit5","title":"","type":"app","bounce":1,"scale":1},
		{"file":"BMA_CO.Phonics_Lv3_Unit7","title":"","type":"app","bounce":1,"scale":1},
		{"file":"BMA_CO.Phonics_Lv3_Unit10","title":"","type":"app","bounce":1,"scale":1},
		{"file":"com.arent.myfirsttangrams","title":"","type":"app","bounce":1,"scale":1},
		{"file":"com.aruhat.mobileapps.animalabc","title":"","type":"app","bounce":1,"scale":1},
		{"file":"com.babyfirsttv.larrythingsthatgo","title":"","type":"app","bounce":1,"scale":1},
		{"file":"com.dornbachs.zebra","title":"","type":"app","bounce":1,"scale":1},
		{"file":"com.goatella.beginningblends","title":"","type":"app","bounce":1,"scale":1},
		{"file":"com.intellijoy.sightwords","title":"","type":"app","bounce":1,"scale":1},
		{"file":"com.oncilla.LetterTracing","title":"","type":"app","bounce":1,"scale":1},
		{"file":"com.tomatointeractive.gmz","title":"","type":"app","bounce":1,"scale":1},
		{"file":"com.zoodles.book.jackandthebeanstalk","title":"","type":"app","bounce":1,"scale":1},
		{"file":"com.zoodles.book.littleredridinghood","title":"","type":"app","bounce":1,"scale":1},
		{"file":"com.zoodles.book.thecountrymouseandthecitymouse","title":"","type":"app","bounce":1,"scale":1},
		{"file":"com.zoodles.book.theelvesandtheshoemaker","title":"","type":"app","bounce":1,"scale":1},
        ]
}